Metadata-Version: 2.1
Name: cloudy-sql
Version: 0.0.0.4
Summary: A Jupyter magics extension designed for seamless interaction with Snowflake
Home-page: https://github.com/hashmapinc/sales-and-marketing/pocs/sam-kohlleffel-poc/pandas-cloudy-extension
Author: Hashmap, Inc
Author-email: accelerators@hashmapinc.com
License: UNKNOWN
Platform: UNKNOWN
Classifier: Programming Language :: Python :: 3
Classifier: License :: OSI Approved :: Apache Software License
Classifier: Operating System :: OS Independent
Classifier: Development Status :: 3 - Alpha
Requires-Python: >=3.7
